MANIFEST.in
README.md
requirements.txt
setup.cfg
setup.py
src/myrappsql.egg-info/PKG-INFO
src/myrappsql.egg-info/SOURCES.txt
src/myrappsql.egg-info/dependency_links.txt
src/myrappsql.egg-info/top_level.txt
src/rappmysql/__init__.py
src/rappmysql/control.py
src/rappmysql/online.py
src/rappmysql/pass_check.py
src/rappmysql/static/heroku.ini
src/rappmysql/static/kalendar.ini
src/rappmysql/static/wdb.ini
src/rappmysql/templates/base.html
src/rappmysql/templates/blabla.html
src/rappmysql/templates/cheltuieli.html
src/rappmysql/templates/expenses.html
src/rappmysql/templates/index.html
src/rappmysql/templates/kalendar.html
src/rappmysql/templates/login.html
src/rappmysql/templates/masina.html
src/rappmysql/templates/navbar.html
src/rappmysql/templates/register.html